[
    {
        "crawl_time": "2021-05-24/17",
        "rank": 1,
        "date": "2021.05.24. 오전 8:32",
        "url": "https://news.naver.com/main/ranking/read.nhn?mode=LSD&mid=shm&sid1=001&oid=092&aid=0002222783&rankingType=RANKING",
        "title": "비트코인 반토막…美中 압박에 '날개 없는 추락'",
        "press": "ZDNet Korea",
        "n_reaction_good": 39,
        "n_reaction_warm": 6,
        "n_reaction_sad": 1,
        "n_reaction_angry": 3,
        "n_reaction_want": 2,
        "n_reactions": 51,
        "n_view": 1389,
        "n_comment": 41,
        "keyword": [
            "비트코인"
        ]
    },
    {
        "crawl_time": "2021-05-24/17",
        "rank": 2,
        "date": "2021.05.24. 오전 10:54",
        "url": "https://news.naver.com/main/ranking/read.nhn?mode=LSD&mid=shm&sid1=001&oid=092&aid=0002222826&rankingType=RANKING",
        "title": "아이폰13 루머 총정리…어떻게 나올까",
        "press": "ZDNet Korea",
        "n_reaction_good": 4,
        "n_reaction_warm": 0,
        "n_reaction_sad": 0,
        "n_reaction_angry": 9,
        "n_reaction_want": 1,
        "n_reactions": 14,
        "n_view": 1259,
        "n_comment": 11,
        "keyword": [
            "아이폰13"
        ]
    },
    {
        "crawl_time": "2021-05-24/17",
        "rank": 3,
        "date": "2021.05.24. 오후 12:10",
        "url": "https://news.naver.com/main/ranking/read.nhn?mode=LSD&mid=shm&sid1=001&oid=092&aid=0002222842&rankingType=RANKING",
        "title": "LG, '롤러블폰' 출시 없지만 만든다...왜?",
        "press": "ZDNet Korea",
        "n_reaction_good": 6,
        "n_reaction_warm": 0,
        "n_reaction_sad": 4,
        "n_reaction_angry": 0,
        "n_reaction_want": 1,
        "n_reactions": 11,
        "n_view": 680,
        "n_comment": 15,
        "keyword": [
            "롤러블폰",
            "LG"
        ]
    },
    {
        "crawl_time": "2021-05-24/17",
        "rank": 4,
        "date": "2021.05.24. 오전 8:21",
        "url": "https://news.naver.com/main/ranking/read.nhn?mode=LSD&mid=shm&sid1=001&oid=092&aid=0002222782&rankingType=RANKING",
        "title": "스포티파이, 애플워치에 오프라인 음악 서비스",
        "press": "ZDNet Korea",
        "n_reaction_good": 2,
        "n_reaction_warm": 0,
        "n_reaction_sad": 0,
        "n_reaction_angry": 0,
        "n_reaction_want": 0,
        "n_reactions": 2,
        "n_view": 535,
        "n_comment": 3,
        "keyword": [
            "애플워치"
        ]
    },
    {
        "crawl_time": "2021-05-24/17",
        "rank": 5,
        "date": "2021.05.24. 오후 2:33",
        "url": "https://news.naver.com/main/ranking/read.nhn?mode=LSD&mid=shm&sid1=001&oid=092&aid=0002222855&rankingType=RANKING",
        "title": "애플·에픽 소송 판사, 팀 쿡 왜 강하게 압박했나",
        "press": "ZDNet Korea",
        "n_reaction_good": 6,
        "n_reaction_warm": 1,
        "n_reaction_sad": 0,
        "n_reaction_angry": 0,
        "n_reaction_want": 1,
        "n_reactions": 8,
        "n_view": 444,
        "n_comment": 0,
        "keyword": [
            "에픽",
            "판사",
            "애플"
        ]
    },
    {
        "crawl_time": "2021-05-24/17",
        "rank": 6,
        "date": "2021.05.24. 오전 10:39",
        "url": "https://news.naver.com/main/ranking/read.nhn?mode=LSD&mid=shm&sid1=001&oid=092&aid=0002222821&rankingType=RANKING",
        "title": "엔씨소프트, 트릭스터M으로 웃었다...매출 애플 1위·구글 3위",
        "press": "ZDNet Korea",
        "n_reaction_good": 10,
        "n_reaction_warm": 0,
        "n_reaction_sad": 0,
        "n_reaction_angry": 13,
        "n_reaction_want": 0,
        "n_reactions": 23,
        "n_view": 349,
        "n_comment": 34,
        "keyword": [
            "애플",
            "구글",
            "트릭스터M",
            "엔씨소프트"
        ]
    },
    {
        "crawl_time": "2021-05-24/17",
        "rank": 7,
        "date": "2021.05.23. 오후 1:58",
        "url": "https://news.naver.com/main/ranking/read.nhn?mode=LSD&mid=shm&sid1=001&oid=092&aid=0002222770&rankingType=RANKING",
        "title": "\"삼성바이오 mRNA백신 국내 첫 생산 의미깊다\"",
        "press": "ZDNet Korea",
        "n_reaction_good": 46,
        "n_reaction_warm": 2,
        "n_reaction_sad": 1,
        "n_reaction_angry": 72,
        "n_reaction_want": 0,
        "n_reactions": 121,
        "n_view": 255,
        "n_comment": 90,
        "keyword": [
            "삼성바이오"
        ]
    },
    {
        "crawl_time": "2021-05-24/17",
        "rank": 8,
        "date": "2021.05.24. 오전 7:55",
        "url": "https://news.naver.com/main/ranking/read.nhn?mode=LSD&mid=shm&sid1=001&oid=092&aid=0002222780&rankingType=RANKING",
        "title": "로봇이 커피타고 배송까지...비대면 시대 新풍경",
        "press": "ZDNet Korea",
        "n_reaction_good": 2,
        "n_reaction_warm": 1,
        "n_reaction_sad": 1,
        "n_reaction_angry": 1,
        "n_reaction_want": 0,
        "n_reactions": 5,
        "n_view": 243,
        "n_comment": 4,
        "keyword": [
            "커피"
        ]
    },
    {
        "crawl_time": "2021-05-24/17",
        "rank": 9,
        "date": "2021.05.24. 오전 9:22",
        "url": "https://news.naver.com/main/ranking/read.nhn?mode=LSD&mid=shm&sid1=001&oid=092&aid=0002222798&rankingType=RANKING",
        "title": "우주여행, 성큼 다가왔다…버진갤럭틱, 2년 만에 우주 시험비행 성공",
        "press": "ZDNet Korea",
        "n_reaction_good": 8,
        "n_reaction_warm": 1,
        "n_reaction_sad": 0,
        "n_reaction_angry": 0,
        "n_reaction_want": 1,
        "n_reactions": 10,
        "n_view": 231,
        "n_comment": 5,
        "keyword": [
            "버진갤럭틱"
        ]
    },
    {
        "crawl_time": "2021-05-24/17",
        "rank": 10,
        "date": "2021.05.24. 오전 10:57",
        "url": "https://news.naver.com/main/ranking/read.nhn?mode=LSD&mid=shm&sid1=001&oid=092&aid=0002222827&rankingType=RANKING",
        "title": "담원 기아, 2021 MSI 준우승...LCK 롤드컵 시드권 4장 확보",
        "press": "ZDNet Korea",
        "n_reaction_good": 8,
        "n_reaction_warm": 0,
        "n_reaction_sad": 0,
        "n_reaction_angry": 3,
        "n_reaction_want": 0,
        "n_reactions": 11,
        "n_view": 209,
        "n_comment": 6,
        "keyword": [
            "롤드컵",
            "MSI",
            "LCK"
        ]
    },
    {
        "crawl_time": "2021-05-24/17",
        "rank": 11,
        "date": "2021.05.20. 오후 1:39",
        "url": "https://news.naver.com/main/ranking/read.nhn?mode=LSD&mid=shm&sid1=001&oid=092&aid=0002222561&rankingType=RANKING",
        "title": "\"애플워치7, 디자인 확 바뀐다\"... 각진 모서리·그린 컬러 추가 전망",
        "press": "ZDNet Korea",
        "n_reaction_good": 28,
        "n_reaction_warm": 0,
        "n_reaction_sad": 0,
        "n_reaction_angry": 4,
        "n_reaction_want": 8,
        "n_reactions": 40,
        "n_view": 156,
        "n_comment": 22,
        "keyword": [
            "애플워치7"
        ]
    },
    {
        "crawl_time": "2021-05-24/17",
        "rank": 12,
        "date": "2021.05.24. 오전 9:51",
        "url": "https://news.naver.com/main/ranking/read.nhn?mode=LSD&mid=shm&sid1=001&oid=092&aid=0002222807&rankingType=RANKING",
        "title": "코로나로 공유킥보드 인기...‘지쿠터’ 설치 상승률 1위",
        "press": "ZDNet Korea",
        "n_reaction_good": 1,
        "n_reaction_warm": 0,
        "n_reaction_sad": 0,
        "n_reaction_angry": 1,
        "n_reaction_want": 0,
        "n_reactions": 2,
        "n_view": 122,
        "n_comment": 8,
        "keyword": [
            "지쿠터",
            "코로나"
        ]
    },
    {
        "crawl_time": "2021-05-24/17",
        "rank": 13,
        "date": "2021.05.24. 오전 10:32",
        "url": "https://news.naver.com/main/ranking/read.nhn?mode=LSD&mid=shm&sid1=001&oid=092&aid=0002222818&rankingType=RANKING",
        "title": "하만 JBL, 스포츠용 노캔 무선 이어폰 출시",
        "press": "ZDNet Korea",
        "n_reaction_good": 0,
        "n_reaction_warm": 0,
        "n_reaction_sad": 0,
        "n_reaction_angry": 0,
        "n_reaction_want": 0,
        "n_reactions": 0,
        "n_view": 113,
        "n_comment": 1,
        "keyword": []
    },
    {
        "crawl_time": "2021-05-24/17",
        "rank": 14,
        "date": "2021.05.24. 오후 2:27",
        "url": "https://news.naver.com/main/ranking/read.nhn?mode=LSD&mid=shm&sid1=001&oid=092&aid=0002222854&rankingType=RANKING",
        "title": "한국은행, CBDC 모의실험 용역 사업자 공개 입찰",
        "press": "ZDNet Korea",
        "n_reaction_good": 0,
        "n_reaction_warm": 0,
        "n_reaction_sad": 0,
        "n_reaction_angry": 0,
        "n_reaction_want": 0,
        "n_reactions": 0,
        "n_view": 84,
        "n_comment": 0,
        "keyword": [
            "한국은행",
            "사업자",
            "CBDC"
        ]
    },
    {
        "crawl_time": "2021-05-24/17",
        "rank": 15,
        "date": "2021.05.24. 오전 10:08",
        "url": "https://news.naver.com/main/ranking/read.nhn?mode=LSD&mid=shm&sid1=001&oid=092&aid=0002222814&rankingType=RANKING",
        "title": "니콘, 거리측정기 '쿨샷' 신제품 3종 출시",
        "press": "ZDNet Korea",
        "n_reaction_good": 0,
        "n_reaction_warm": 0,
        "n_reaction_sad": 0,
        "n_reaction_angry": 0,
        "n_reaction_want": 0,
        "n_reactions": 0,
        "n_view": 67,
        "n_comment": 0,
        "keyword": [
            "니콘",
            "쿨샷"
        ]
    },
    {
        "crawl_time": "2021-05-24/17",
        "rank": 16,
        "date": "2021.05.24. 오전 10:00",
        "url": "https://news.naver.com/main/ranking/read.nhn?mode=LSD&mid=shm&sid1=001&oid=092&aid=0002222810&rankingType=RANKING",
        "title": "BMW코리아, 온라인 익스클루시브 모델 2종 출시",
        "press": "ZDNet Korea",
        "n_reaction_good": 0,
        "n_reaction_warm": 0,
        "n_reaction_sad": 0,
        "n_reaction_angry": 0,
        "n_reaction_want": 0,
        "n_reactions": 0,
        "n_view": 64,
        "n_comment": 0,
        "keyword": [
            "BMW코리아"
        ]
    },
    {
        "crawl_time": "2021-05-24/17",
        "rank": 17,
        "date": "2021.05.24. 오전 11:01",
        "url": "https://news.naver.com/main/ranking/read.nhn?mode=LSD&mid=shm&sid1=001&oid=092&aid=0002222830&rankingType=RANKING",
        "title": "삼성전자, 대화면 스마트 모니터 'M7 43형 UHD' 출시",
        "press": "ZDNet Korea",
        "n_reaction_good": 1,
        "n_reaction_warm": 0,
        "n_reaction_sad": 0,
        "n_reaction_angry": 0,
        "n_reaction_want": 0,
        "n_reactions": 1,
        "n_view": 57,
        "n_comment": 0,
        "keyword": [
            "삼성전자"
        ]
    },
    {
        "crawl_time": "2021-05-24/17",
        "rank": 18,
        "date": "2021.05.24. 오후 2:19",
        "url": "https://news.naver.com/main/ranking/read.nhn?mode=LSD&mid=shm&sid1=001&oid=092&aid=0002222853&rankingType=RANKING",
        "title": "\"中企 ESG, 안전·인권 등 사회적책임부터 접근해야\"",
        "press": "ZDNet Korea",
        "n_reaction_good": 0,
        "n_reaction_warm": 0,
        "n_reaction_sad": 0,
        "n_reaction_angry": 1,
        "n_reaction_want": 0,
        "n_reactions": 1,
        "n_view": 54,
        "n_comment": 0,
        "keyword": [
            "ESG"
        ]
    },
    {
        "crawl_time": "2021-05-24/17",
        "rank": 19,
        "date": "2021.05.24. 오전 10:02",
        "url": "https://news.naver.com/main/ranking/read.nhn?mode=LSD&mid=shm&sid1=001&oid=092&aid=0002222812&rankingType=RANKING",
        "title": "삼성전자, '스마트 키보드 트리오 500' 출시",
        "press": "ZDNet Korea",
        "n_reaction_good": 0,
        "n_reaction_warm": 0,
        "n_reaction_sad": 0,
        "n_reaction_angry": 0,
        "n_reaction_want": 0,
        "n_reactions": 0,
        "n_view": 49,
        "n_comment": 0,
        "keyword": [
            "삼성전자"
        ]
    },
    {
        "crawl_time": "2021-05-24/17",
        "rank": 20,
        "date": "2021.05.24. 오전 8:57",
        "url": "https://news.naver.com/main/ranking/read.nhn?mode=LSD&mid=shm&sid1=001&oid=092&aid=0002222789&rankingType=RANKING",
        "title": "바이두-칭화대, 센서 뺀 'V2X' 자율주행 개발",
        "press": "ZDNet Korea",
        "n_reaction_good": 3,
        "n_reaction_warm": 0,
        "n_reaction_sad": 0,
        "n_reaction_angry": 1,
        "n_reaction_want": 1,
        "n_reactions": 5,
        "n_view": 42,
        "n_comment": 0,
        "keyword": [
            "칭화대",
            "바이두"
        ]
    },
    {
        "crawl_time": "2021-05-24/17",
        "rank": 1,
        "date": "2021.05.24. 오전 11:20",
        "url": "https://news.naver.com/main/ranking/read.nhn?mode=LSD&mid=shm&sid1=001&oid=215&aid=0000959892&rankingType=RANKING",
        "title": "6학년이 3학년 때려 '전치 12주'…그냥 집에 보낸 학교",
        "press": "한국경제TV",
        "n_reaction_good": 1,
        "n_reaction_warm": 0,
        "n_reaction_sad": 0,
        "n_reaction_angry": 437,
        "n_reaction_want": 7,
        "n_reactions": 445,
        "n_view": 10329,
        "n_comment": 176,
        "keyword": []
    },
    {
        "crawl_time": "2021-05-24/17",
        "rank": 2,
        "date": "2021.05.24. 오후 1:45",
        "url": "https://news.naver.com/main/ranking/read.nhn?mode=LSD&mid=shm&sid1=001&oid=215&aid=0000959927&rankingType=RANKING",
        "title": "'10만전자' 간다던 삼성전자…증권사 목표가 줄하향",
        "press": "한국경제TV",
        "n_reaction_good": 3,
        "n_reaction_warm": 1,
        "n_reaction_sad": 0,
        "n_reaction_angry": 26,
        "n_reaction_want": 0,
        "n_reactions": 30,
        "n_view": 5844,
        "n_comment": 25,
        "keyword": [
            "삼성전자"
        ]
    },
    {
        "crawl_time": "2021-05-24/17",
        "rank": 3,
        "date": "2021.05.24. 오전 10:47",
        "url": "https://news.naver.com/main/ranking/read.nhn?mode=LSD&mid=shm&sid1=001&oid=215&aid=0000959877&rankingType=RANKING",
        "title": "\"투자실패 불만\"…차 몰고 인파로 돌진한 30대",
        "press": "한국경제TV",
        "n_reaction_good": 18,
        "n_reaction_warm": 12,
        "n_reaction_sad": 3,
        "n_reaction_angry": 139,
        "n_reaction_want": 1,
        "n_reactions": 173,
        "n_view": 5009,
        "n_comment": 112,
        "keyword": []
    },
    {
        "crawl_time": "2021-05-24/17",
        "rank": 4,
        "date": "2021.05.24. 오전 8:03",
        "url": "https://news.naver.com/main/ranking/read.nhn?mode=LSD&mid=shm&sid1=001&oid=215&aid=0000959795&rankingType=RANKING",
        "title": "'생일파티 한다' SNS 게시...\"2,500명 몰려왔다\"",
        "press": "한국경제TV",
        "n_reaction_good": 6,
        "n_reaction_warm": 0,
        "n_reaction_sad": 5,
        "n_reaction_angry": 36,
        "n_reaction_want": 1,
        "n_reactions": 48,
        "n_view": 2914,
        "n_comment": 27,
        "keyword": []
    },
    {
        "crawl_time": "2021-05-24/17",
        "rank": 5,
        "date": "2021.05.24. 오전 10:53",
        "url": "https://news.naver.com/main/ranking/read.nhn?mode=LSD&mid=shm&sid1=001&oid=215&aid=0000959881&rankingType=RANKING",
        "title": "주택·상가 빌리는 MZ세대 급증…\"낮은 소득 영향\"",
        "press": "한국경제TV",
        "n_reaction_good": 1,
        "n_reaction_warm": 2,
        "n_reaction_sad": 1,
        "n_reaction_angry": 11,
        "n_reaction_want": 2,
        "n_reactions": 17,
        "n_view": 2336,
        "n_comment": 6,
        "keyword": []
    },
    {
        "crawl_time": "2021-05-24/17",
        "rank": 6,
        "date": "2021.05.24. 오전 8:58",
        "url": "https://news.naver.com/main/ranking/read.nhn?mode=LSD&mid=shm&sid1=001&oid=215&aid=0000959814&rankingType=RANKING",
        "title": "노벨상 수상자 \"비트코인 산적 없어...암호화폐 가치 모호\"",
        "press": "한국경제TV",
        "n_reaction_good": 26,
        "n_reaction_warm": 0,
        "n_reaction_sad": 0,
        "n_reaction_angry": 6,
        "n_reaction_want": 2,
        "n_reactions": 34,
        "n_view": 1673,
        "n_comment": 22,
        "keyword": [
            "비트코인",
            "노벨상",
            "수상자"
        ]
    },
    {
        "crawl_time": "2021-05-24/17",
        "rank": 7,
        "date": "2021.05.24. 오후 12:43",
        "url": "https://news.naver.com/main/ranking/read.nhn?mode=LSD&mid=shm&sid1=001&oid=215&aid=0000959912&rankingType=RANKING",
        "title": "10대 의붓딸 강간하고 동영상 찍은 30대…징역 15년",
        "press": "한국경제TV",
        "n_reaction_good": 0,
        "n_reaction_warm": 0,
        "n_reaction_sad": 1,
        "n_reaction_angry": 241,
        "n_reaction_want": 2,
        "n_reactions": 244,
        "n_view": 1655,
        "n_comment": 109,
        "keyword": [
            "징역",
            "강간",
            "의붓딸"
        ]
    },
    {
        "crawl_time": "2021-05-24/17",
        "rank": 8,
        "date": "2021.05.24. 오전 11:08",
        "url": "https://news.naver.com/main/ranking/read.nhn?mode=LSD&mid=shm&sid1=001&oid=215&aid=0000959885&rankingType=RANKING",
        "title": "\"모더나 백신 5.5만회분, 6월 중순부터 공급\"",
        "press": "한국경제TV",
        "n_reaction_good": 27,
        "n_reaction_warm": 2,
        "n_reaction_sad": 0,
        "n_reaction_angry": 91,
        "n_reaction_want": 2,
        "n_reactions": 122,
        "n_view": 1369,
        "n_comment": 76,
        "keyword": []
    },
    {
        "crawl_time": "2021-05-24/17",
        "rank": 9,
        "date": "2021.05.24. 오후 3:11",
        "url": "https://news.naver.com/main/ranking/read.nhn?mode=LSD&mid=shm&sid1=001&oid=215&aid=0000959960&rankingType=RANKING",
        "title": "현대차·모비스, 반도체 수급 차질로 생산중단…셧다운 도미노 본격화",
        "press": "한국경제TV",
        "n_reaction_good": 0,
        "n_reaction_warm": 0,
        "n_reaction_sad": 0,
        "n_reaction_angry": 1,
        "n_reaction_want": 0,
        "n_reactions": 1,
        "n_view": 1309,
        "n_comment": 1,
        "keyword": [
            "현대차",
            "모비스"
        ]
    },
    {
        "crawl_time": "2021-05-24/17",
        "rank": 10,
        "date": "2021.05.24. 오전 11:00",
        "url": "https://news.naver.com/main/ranking/read.nhn?mode=LSD&mid=shm&sid1=001&oid=215&aid=0000959883&rankingType=RANKING",
        "title": "삼성 스마트 모니터 전 세계 출시…43형 UHD 신제품 추가",
        "press": "한국경제TV",
        "n_reaction_good": 11,
        "n_reaction_warm": 0,
        "n_reaction_sad": 0,
        "n_reaction_angry": 0,
        "n_reaction_want": 2,
        "n_reactions": 13,
        "n_view": 953,
        "n_comment": 6,
        "keyword": [
            "삼성"
        ]
    },
    {
        "crawl_time": "2021-05-24/17",
        "rank": 11,
        "date": "2021.05.24. 오전 10:28",
        "url": "https://news.naver.com/main/ranking/read.nhn?mode=LSD&mid=shm&sid1=001&oid=215&aid=0000959868&rankingType=RANKING",
        "title": "中 비트코인 채굴금지 '나비효과'...이란 '정전대란'",
        "press": "한국경제TV",
        "n_reaction_good": 3,
        "n_reaction_warm": 1,
        "n_reaction_sad": 0,
        "n_reaction_angry": 7,
        "n_reaction_want": 2,
        "n_reactions": 13,
        "n_view": 894,
        "n_comment": 9,
        "keyword": [
            "비트코인"
        ]
    },
    {
        "crawl_time": "2021-05-24/17",
        "rank": 12,
        "date": "2021.05.24. 오전 11:20",
        "url": "https://news.naver.com/main/ranking/read.nhn?mode=LSD&mid=shm&sid1=001&oid=215&aid=0000959890&rankingType=RANKING",
        "title": "서머스 전 美재무 \"암호화폐, 금 대안자산될 가능성 있어\"",
        "press": "한국경제TV",
        "n_reaction_good": 8,
        "n_reaction_warm": 1,
        "n_reaction_sad": 0,
        "n_reaction_angry": 9,
        "n_reaction_want": 0,
        "n_reactions": 18,
        "n_view": 844,
        "n_comment": 12,
        "keyword": [
            "서머스"
        ]
    },
    {
        "crawl_time": "2021-05-24/17",
        "rank": 13,
        "date": "2021.05.24. 오후 2:56",
        "url": "https://news.naver.com/main/ranking/read.nhn?mode=LSD&mid=shm&sid1=001&oid=215&aid=0000959954&rankingType=RANKING",
        "title": "[단독] 박성호 행장 첫 작품은 '이커머스'…\"우리가 직접 판다\"",
        "press": "한국경제TV",
        "n_reaction_good": 2,
        "n_reaction_warm": 0,
        "n_reaction_sad": 0,
        "n_reaction_angry": 0,
        "n_reaction_want": 0,
        "n_reactions": 2,
        "n_view": 638,
        "n_comment": 0,
        "keyword": [
            "박성호",
            "행장"
        ]
    },
    {
        "crawl_time": "2021-05-24/17",
        "rank": 14,
        "date": "2021.05.24. 오후 3:14",
        "url": "https://news.naver.com/main/ranking/read.nhn?mode=LSD&mid=shm&sid1=001&oid=215&aid=0000959961&rankingType=RANKING",
        "title": "여고생에 \"술 한잔하자\" 집적댄 40대 경찰 인사조치",
        "press": "한국경제TV",
        "n_reaction_good": 0,
        "n_reaction_warm": 0,
        "n_reaction_sad": 0,
        "n_reaction_angry": 15,
        "n_reaction_want": 0,
        "n_reactions": 15,
        "n_view": 564,
        "n_comment": 10,
        "keyword": [
            "경찰"
        ]
    },
    {
        "crawl_time": "2021-05-24/17",
        "rank": 15,
        "date": "2021.05.24. 오후 2:44",
        "url": "https://news.naver.com/main/ranking/read.nhn?mode=LSD&mid=shm&sid1=001&oid=215&aid=0000959952&rankingType=RANKING",
        "title": "금융위, 산은·수은 등 13개 기관과 '기후변화 대응' TCFD 지지선언",
        "press": "한국경제TV",
        "n_reaction_good": 1,
        "n_reaction_warm": 0,
        "n_reaction_sad": 0,
        "n_reaction_angry": 3,
        "n_reaction_want": 0,
        "n_reactions": 4,
        "n_view": 442,
        "n_comment": 1,
        "keyword": [
            "TCFD",
            "금융위",
            "산은",
            "수은"
        ]
    },
    {
        "crawl_time": "2021-05-24/17",
        "rank": 16,
        "date": "2021.05.24. 오후 1:19",
        "url": "https://news.naver.com/main/ranking/read.nhn?mode=LSD&mid=shm&sid1=001&oid=215&aid=0000959920&rankingType=RANKING",
        "title": "AZ백신 맞은 20대 여성 소방공무원, '급성 횡단성 척수염'",
        "press": "한국경제TV",
        "n_reaction_good": 4,
        "n_reaction_warm": 1,
        "n_reaction_sad": 7,
        "n_reaction_angry": 88,
        "n_reaction_want": 0,
        "n_reactions": 100,
        "n_view": 364,
        "n_comment": 28,
        "keyword": [
            "소방공무원"
        ]
    },
    {
        "crawl_time": "2021-05-24/17",
        "rank": 17,
        "date": "2021.05.24. 오전 11:52",
        "url": "https://news.naver.com/main/ranking/read.nhn?mode=LSD&mid=shm&sid1=001&oid=215&aid=0000959900&rankingType=RANKING",
        "title": "대구 유흥주점발 확진자 158명…\"변이 가능성 높아\"",
        "press": "한국경제TV",
        "n_reaction_good": 0,
        "n_reaction_warm": 0,
        "n_reaction_sad": 0,
        "n_reaction_angry": 2,
        "n_reaction_want": 1,
        "n_reactions": 3,
        "n_view": 329,
        "n_comment": 1,
        "keyword": [
            "확진자"
        ]
    },
    {
        "crawl_time": "2021-05-24/17",
        "rank": 18,
        "date": "2021.05.24. 오전 8:46",
        "url": "https://news.naver.com/main/ranking/read.nhn?mode=LSD&mid=shm&sid1=001&oid=215&aid=0000959810&rankingType=RANKING",
        "title": "20조 쏘는 삼성·SK...\"한미 수혜주 6종목\"",
        "press": "한국경제TV",
        "n_reaction_good": 3,
        "n_reaction_warm": 0,
        "n_reaction_sad": 0,
        "n_reaction_angry": 26,
        "n_reaction_want": 0,
        "n_reactions": 29,
        "n_view": 297,
        "n_comment": 9,
        "keyword": [
            "SK",
            "삼성"
        ]
    },
    {
        "crawl_time": "2021-05-24/17",
        "rank": 19,
        "date": "2021.05.24. 오후 3:10",
        "url": "https://news.naver.com/main/ranking/read.nhn?mode=LSD&mid=shm&sid1=001&oid=215&aid=0000959959&rankingType=RANKING",
        "title": "'선박부족'에 HMM, 24번째 임시선박 출항…이달만 4번째",
        "press": "한국경제TV",
        "n_reaction_good": 5,
        "n_reaction_warm": 0,
        "n_reaction_sad": 0,
        "n_reaction_angry": 0,
        "n_reaction_want": 0,
        "n_reactions": 5,
        "n_view": 294,
        "n_comment": 0,
        "keyword": [
            "HMM"
        ]
    },
    {
        "crawl_time": "2021-05-24/17",
        "rank": 20,
        "date": "2021.05.24. 오전 8:12",
        "url": "https://news.naver.com/main/ranking/read.nhn?mode=LSD&mid=shm&sid1=001&oid=215&aid=0000959800&rankingType=RANKING",
        "title": "머스크, 뜬금 비트코인 지지 표명…투자자 분노 [글로벌이슈]",
        "press": "한국경제TV",
        "n_reaction_good": 9,
        "n_reaction_warm": 2,
        "n_reaction_sad": 2,
        "n_reaction_angry": 35,
        "n_reaction_want": 2,
        "n_reactions": 50,
        "n_view": 212,
        "n_comment": 50,
        "keyword": [
            "비트코인",
            "머스크",
            "투자자"
        ]
    },
    {
        "crawl_time": "2021-05-24/17",
        "rank": 1,
        "date": "2021.05.24. 오전 10:02",
        "url": "https://news.naver.com/main/ranking/read.nhn?mode=LSD&mid=shm&sid1=001&oid=262&aid=0000014488&rankingType=RANKING",
        "title": "김웅 “윤석열, 반드시 국민의힘 온다… 김종인, 내게 ‘자신만의 정치하라’”",
        "press": "신동아",
        "n_reaction_good": 55,
        "n_reaction_warm": 1,
        "n_reaction_sad": 0,
        "n_reaction_angry": 86,
        "n_reaction_want": 0,
        "n_reactions": 142,
        "n_view": 1357,
        "n_comment": -1,
        "keyword": [
            "윤석열",
            "국민",
            "김웅",
            "김종인"
        ]
    },
    {
        "crawl_time": "2021-05-24/17",
        "rank": 2,
        "date": "2021.05.24. 오전 10:02",
        "url": "https://news.naver.com/main/ranking/read.nhn?mode=LSD&mid=shm&sid1=001&oid=262&aid=0000014489&rankingType=RANKING",
        "title": "‘탄핵 내전’ 국민의힘, 野 대선 윤석열·김동연 빅매치?",
        "press": "신동아",
        "n_reaction_good": 0,
        "n_reaction_warm": 0,
        "n_reaction_sad": 0,
        "n_reaction_angry": 7,
        "n_reaction_want": 1,
        "n_reactions": 8,
        "n_view": 197,
        "n_comment": -1,
        "keyword": [
            "윤석열",
            "국민",
            "대선",
            "김동연"
        ]
    },
    {
        "crawl_time": "2021-05-24/17",
        "rank": 3,
        "date": "2021.05.22. 오전 10:02",
        "url": "https://news.naver.com/main/ranking/read.nhn?mode=LSD&mid=shm&sid1=001&oid=262&aid=0000014484&rankingType=RANKING",
        "title": "인구 70% 백신 맞아도 코로나는 계속된다",
        "press": "신동아",
        "n_reaction_good": 10,
        "n_reaction_warm": 0,
        "n_reaction_sad": 9,
        "n_reaction_angry": 45,
        "n_reaction_want": 4,
        "n_reactions": 68,
        "n_view": 179,
        "n_comment": 32,
        "keyword": []
    },
    {
        "crawl_time": "2021-05-24/17",
        "rank": 4,
        "date": "2021.05.23. 오전 10:02",
        "url": "https://news.naver.com/main/ranking/read.nhn?mode=LSD&mid=shm&sid1=001&oid=262&aid=0000014486&rankingType=RANKING",
        "title": "‘대선 잰걸음’…윤석열이 만난 사람들",
        "press": "신동아",
        "n_reaction_good": 116,
        "n_reaction_warm": 3,
        "n_reaction_sad": 0,
        "n_reaction_angry": 7,
        "n_reaction_want": 1,
        "n_reactions": 127,
        "n_view": 77,
        "n_comment": -1,
        "keyword": [
            "윤석열",
            "대선"
        ]
    },
    {
        "crawl_time": "2021-05-24/17",
        "rank": 5,
        "date": "2021.05.23. 오전 10:02",
        "url": "https://news.naver.com/main/ranking/read.nhn?mode=LSD&mid=shm&sid1=001&oid=262&aid=0000014487&rankingType=RANKING",
        "title": "김학의 불법출금이 산불 끄기? 법의 탈 쓴 독재[노정태의 뷰파인더㉟]",
        "press": "신동아",
        "n_reaction_good": 26,
        "n_reaction_warm": 0,
        "n_reaction_sad": 0,
        "n_reaction_angry": 29,
        "n_reaction_want": 2,
        "n_reactions": 57,
        "n_view": 69,
        "n_comment": -1,
        "keyword": [
            "노정태",
            "뷰파인더",
            "김학"
        ]
    },
    {
        "crawl_time": "2021-05-24/17",
        "rank": 6,
        "date": "2021.05.22. 오전 10:02",
        "url": "https://news.naver.com/main/ranking/read.nhn?mode=LSD&mid=shm&sid1=001&oid=262&aid=0000014483&rankingType=RANKING",
        "title": "[베이스볼 비키니] 롯데 자이언츠 감독 교체, 단장 야구의 승리?",
        "press": "신동아",
        "n_reaction_good": 24,
        "n_reaction_warm": 0,
        "n_reaction_sad": 0,
        "n_reaction_angry": 5,
        "n_reaction_want": 1,
        "n_reactions": 30,
        "n_view": 59,
        "n_comment": 32,
        "keyword": [
            "베이스볼",
            "야구",
            "비키니",
            "단장"
        ]
    },
    {
        "crawl_time": "2021-05-24/17",
        "rank": 7,
        "date": "2021.05.24. 오후 3:34",
        "url": "https://news.naver.com/main/ranking/read.nhn?mode=LSD&mid=shm&sid1=001&oid=262&aid=0000014490&rankingType=RANKING",
        "title": "[말前말後] “최고의 순방, 최고의 회담” vs “자화자찬”",
        "press": "신동아",
        "n_reaction_good": 0,
        "n_reaction_warm": 0,
        "n_reaction_sad": 0,
        "n_reaction_angry": 2,
        "n_reaction_want": 0,
        "n_reactions": 2,
        "n_view": 33,
        "n_comment": -1,
        "keyword": []
    }
]